cirqtools/__init__.py
cirqtools/classical_simulator.py
cirqtools/feynman_path_simulator.py
cirqtools/qudit/__init__.py
cirqtools/qudit/common_gates.py
cirqtools/qudit/extension_gates.py
cirqtools/qudit/three_qutrit_gates.py
cirqtools/qutrit/__init__.py
cirqtools/qutrit/common_gates.py
cirqtools-0.2.0.dist-info/METADATA
cirqtools-0.2.0.dist-info/WHEEL
cirqtools-0.2.0.dist-info/top_level.txt
cirqtools-0.2.0.dist-info/RECORD
